tomlparse/__init__.py
tomlparse/argparse.py
tomlparse-1.1.3.dist-info/METADATA
tomlparse-1.1.3.dist-info/WHEEL
tomlparse-1.1.3.dist-info/licenses/LICENSE
tomlparse-1.1.3.dist-info/RECORD
