Metadata-Version: 2.4
Name: tomlparse
Version: 1.1.3
Summary: This is a template repository for Python projects that use Poetry for their dependency management.
License-File: LICENSE
Author: florianmahner
Author-email: florian.mahner@gmail.com
Requires-Python: >=3.8,<4.0
Classifier: Programming Language :: Python :: 3
Classifier: Programming Language :: Python :: 3.8
Classifier: Programming Language :: Python :: 3.9
Classifier: Programming Language :: Python :: 3.10
Classifier: Programming Language :: Python :: 3.11
Classifier: Programming Language :: Python :: 3.12
Classifier: Programming Language :: Python :: 3.13
Classifier: Programming Language :: Python :: 3.14
Requires-Dist: tomli (>=1.1.0,<2.0.0) ; python_full_version <= "3.11.0"
Requires-Dist: types-toml (>=0.1.3,<0.2.0) ; python_full_version <= "3.11.0"
Project-URL: Documentation, https://florianmahner.github.io/tomlparse/
Project-URL: Repository, https://github.com/florianmahner/tomlparse
